aioqzone/__init__.py
aioqzone/exception.py
aioqzone/message.py
aioqzone/api/__init__.py
aioqzone/api/h5/__init__.py
aioqzone/api/h5/model.py
aioqzone/api/login/__init__.py
aioqzone/api/login/_base.py
aioqzone/model/__init__.py
aioqzone/model/api/__init__.py
aioqzone/model/api/feed.py
aioqzone/model/api/profile.py
aioqzone/model/api/request.py
aioqzone/model/api/response.py
aioqzone/model/protocol/__init__.py
aioqzone/model/protocol/config.py
aioqzone/model/protocol/entity.py
aioqzone/utils/__init__.py
aioqzone/utils/entity.py
aioqzone/utils/regex.py
aioqzone/utils/retry.py
aioqzone/utils/time.py
aioqzone-1.9.5.dist-info/METADATA
aioqzone-1.9.5.dist-info/WHEEL
aioqzone-1.9.5.dist-info/licenses/LICENSE
aioqzone-1.9.5.dist-info/RECORD
