Metadata-Version: 2.4
Name: aioqzone
Version: 1.9.5
Summary: A Python wrapper for Qzone login and H5 APIs.
Project-URL: Repository, https://github.com/aioqzone/aioqzone
Project-URL: Documentation, https://aioqzone.github.io/aioqzone
Project-URL: Bug Tracker, https://github.com/aioqzone/aioqzone/issues
Project-URL: Discussion, https://t.me/aioqzone_chatroom
Author: aioqzone
Maintainer-email: JamzumSum <22952836+JamzumSum@users.noreply.github.com>
License-Expression: AGPL-3.0
License-File: LICENSE
Keywords: asyncio-spider,autologin,qzone-api
Classifier: Development Status :: 4 - Beta
Classifier: Intended Audience :: Developers
Classifier: Topic :: Software Development :: Libraries :: Python Modules
Classifier: Typing :: Typed
Requires-Python: >=3.9
Requires-Dist: pydantic-settings>=2.9.0
Requires-Dist: qqqr
